codedapertures/__init__.py
codedapertures/codedapertures.py
codedapertures-0.12.dist-info/LICENSE
codedapertures-0.12.dist-info/METADATA
codedapertures-0.12.dist-info/WHEEL
codedapertures-0.12.dist-info/top_level.txt
codedapertures-0.12.dist-info/RECORD
