Metadata-Version: 2.1
Name: codedapertures
Version: 0.12
Summary: a python package for generating coded apertures
Home-page: https://github.com/bpops/codedapertures
Author: bpops
License: MIT
License-File: LICENSE
Requires-Dist: pyprimes
Requires-Dist: numpy
Requires-Dist: matplotlib
Requires-Dist: scikit-commpy
Requires-Dist: scipy
